{
  "title": "Başlayalım",
  "intro": "Learn about The Graph, a decentralized protocol for indexing and querying data from blockchains.",
  "shortcuts": {
    "aboutTheGraph": {
      "title": "Graph Hakkında",
      "description": "Graph hakkında daha fazla bilgi edinin"
    },
    "quickStart": {
      "title": "Quick Start",
      "description": "Jump in and start with The Graph"
    },
    "developerFaqs": {
      "title": "Developer FAQs",
      "description": "Frequently asked questions"
    },
    "queryFromAnApplication": {
      "title": "Query from an Application",
      "description": "Learn to query from an application"
    },
    "createASubgraph": {
      "title": "Create a Subgraph",
      "description": "Use Studio to create subgraphs"
    },
    "migrateFromHostedService": {
      "title": "Migrate from the Hosted Service",
      "description": "Migrating subgraphs to The Graph Network"
    }
  },
  "networkRoles": {
    "title": "Network Roles",
    "description": "Learn about The Graph’s network roles.",
    "roles": {
      "developer": {
        "title": "Geliştirici",
        "description": "Bir subgraph oluşturun veya bir dApp'de mevcut subgraph'leri kullanın"
      },
      "indexer": {
        "title": "Dizin Oluşturucu",
        "description": "Verileri endekslemek ve sorguları sunmak için bir node çalıştırın"
      },
      "curator": {
        "title": "Küratör",
        "description": "Subgraph'lerde sinyal vererek verileri düzenleyin"
      },
      "delegator": {
        "title": "Yetkilendiren",
        "description": "GRT'yi Dizin Oluşturuculara devrederek ağı güvenli hale getirin"
      }
    }
  },
  "readMore": "Daha fazlasını okuyun",
  "products": {
    "title": "Ürünler",
    "products": {
      "subgraphStudio": {
        "title": "Subgraph Stüdyosu",
        "description": "Subgraph'ler ve API anahtarları oluşturun, yönetin ve yayınlayın"
      },
      "graphExplorer": {
        "title": "Graph Gezgini",
        "description": "Subgraph'leri keşfedin ve protokolle etkileşime girin"
      },
      "hostedService": {
        "title": "Barındırılan Hizmet",
        "description": "Barındırılan Hizmet üzerinde subgraph'ler oluşturun ve keşfedin"
      }
    }
  },
  "supportedNetworks": {
    "title": "Desteklenen Ağlar",
    "description": "Graph Protokol, Graph Ağı ve Barındırılan Hizmet üzerinde aşağıdaki ağları destekler.",
    "graphNetworkAndHostedService": "Graph Ağı ve Barındırılan Hizmet",
    "hostedService": "Barındırılan Hizmet",
    "betaWarning": "Beta'da."
  }
}
